sinapsis_rf_trackers/__init__.py
sinapsis_rf_trackers/helpers/__init__.py
sinapsis_rf_trackers/helpers/tags.py
sinapsis_rf_trackers/templates/__init__.py
sinapsis_rf_trackers/templates/deepsort_tracker_inference.py
sinapsis_rf_trackers/templates/rf_tracker_base.py
sinapsis_rf_trackers/templates/sort_tracker_inference.py
sinapsis_rf_trackers-0.1.3.dist-info/licenses/LICENSE
sinapsis_rf_trackers-0.1.3.dist-info/METADATA
sinapsis_rf_trackers-0.1.3.dist-info/WHEEL
sinapsis_rf_trackers-0.1.3.dist-info/top_level.txt
sinapsis_rf_trackers-0.1.3.dist-info/RECORD
