Metadata-Version: 2.4
Name: sinapsis-rf-trackers
Version: 0.1.3
Summary: Multi-object tracking templates using SORT and DeepSORT algorithms
Project-URL: Homepage, https://sinapsis.tech
Project-URL: Documentation, https://docs.sinapsis.tech/docs
Project-URL: Tutorials, https://docs.sinapsis.tech/tutorials
Project-URL: Repository, https://github.com/Sinapsis-AI/sinapsis-trackers.git
Requires-Python: >=3.10
License-File: LICENSE
Requires-Dist: sinapsis>=0.2.2
Requires-Dist: sinapsis-data-visualization[visualization-matplotlib]>=0.1.0
Requires-Dist: torch>=2.8.0
Requires-Dist: torchvision>=0.23.0
Requires-Dist: trackers[reid]==2.0.2rc0
Provides-Extra: all
Requires-Dist: sinapsis-rf-trackers[sinapsis-data-readers,sinapsis-data-writers,sinapsis-dfine,sinapsis-ultralytics]; extra == "all"
Provides-Extra: sinapsis-ultralytics
Requires-Dist: sinapsis-ultralytics>=0.1.1; extra == "sinapsis-ultralytics"
Provides-Extra: sinapsis-dfine
Requires-Dist: sinapsis-dfine[training]>=0.1.1; extra == "sinapsis-dfine"
Provides-Extra: sinapsis-data-readers
Requires-Dist: sinapsis-data-readers[opencv]>=0.1.2; extra == "sinapsis-data-readers"
Provides-Extra: sinapsis-data-writers
Requires-Dist: sinapsis-data-writers>=0.1.1; extra == "sinapsis-data-writers"
Dynamic: license-file
